examples/api_tests.py
examples/app_notifications_tests.py
examples/args.py
examples/gshock_server.py
examples/health_test.py
gshock_api/__init__.py
gshock_api/alarms.py
gshock_api/always_connected_watch_filter.py
gshock_api/app_notification.py
gshock_api/cancelable_result.py
gshock_api/casio_constants.py
gshock_api/connection.py
gshock_api/event.py
gshock_api/exceptions.py
gshock_api/gshock_api.py
gshock_api/logger.py
gshock_api/message_dispatcher.py
gshock_api/scanner.py
gshock_api/settings.py
gshock_api/utils.py
gshock_api/watch_info.py
gshock_api/iolib/__init__.py
gshock_api/iolib/alarms_io.py
gshock_api/iolib/app_info_io.py
gshock_api/iolib/app_notification_io.py
gshock_api/iolib/button_pressed_io.py
gshock_api/iolib/connection_protocol.py
gshock_api/iolib/dst_for_world_cities_io.py
gshock_api/iolib/dst_watch_state_io.py
gshock_api/iolib/error_io.py
gshock_api/iolib/events_io.py
gshock_api/iolib/packet.py
gshock_api/iolib/settings_io.py
gshock_api/iolib/time_adjustement_io.py
gshock_api/iolib/time_io.py
gshock_api/iolib/timer_io.py
gshock_api/iolib/unknown_io.py
gshock_api/iolib/watch_condition_io.py
gshock_api/iolib/watch_name_io.py
gshock_api/iolib/world_cities_io.py
gshock_api-2.0.36.dist-info/licenses/LICENSE.txt
gshock_api-2.0.36.dist-info/METADATA
gshock_api-2.0.36.dist-info/WHEEL
gshock_api-2.0.36.dist-info/entry_points.txt
gshock_api-2.0.36.dist-info/top_level.txt
gshock_api-2.0.36.dist-info/RECORD
