Metadata-Version: 2.4
Name: gshock_api
Version: 2.0.36
Summary: Python API for GShock Watches using BLE
Home-page: https://github.com/izivkov/gshock_api/
Author: Ivo Zivkov
Author-email: Ivo Zivkov <izivkov@gmail.com>
License-Expression: MIT
Project-URL: Documentation, https://github.com/izivkov/gshock_api
Platform: any
Classifier: Development Status :: 4 - Beta
Classifier: Programming Language :: Python :: 3
Requires-Python: >=3.12
License-File: LICENSE.txt
Requires-Dist: pydantic>=2.0.0
Requires-Dist: types-requests
Requires-Dist: python-dotenv
Requires-Dist: typing-extensions>=4.12
Requires-Dist: twine>=6.2.0
Provides-Extra: dev
Requires-Dist: basedpyright>=1.31.7; extra == "dev"
Requires-Dist: ruff; extra == "dev"
Requires-Dist: gitingest; extra == "dev"
Requires-Dist: poethepoet; extra == "dev"
Requires-Dist: radon; extra == "dev"
Requires-Dist: vulture; extra == "dev"
Dynamic: license-file
